huzzleuo130.py
huzzleuo130-0.1.dist-info/METADATA
huzzleuo130-0.1.dist-info/WHEEL
huzzleuo130-0.1.dist-info/top_level.txt
huzzleuo130-0.1.dist-info/RECORD
