Metadata-Version: 2.4
Name: huzzleuo130
Version: 0.1
Requires-Dist: requests>=2.25.0
Dynamic: requires-dist
